xixiang/__init__.py
xixiang/exceptions.py
xixiang/models.py
xixiang/services.py
xixiang/urls.py
xixiang-0.3.1.dist-info/LICENSE
xixiang-0.3.1.dist-info/METADATA
xixiang-0.3.1.dist-info/WHEEL
xixiang-0.3.1.dist-info/top_level.txt
xixiang-0.3.1.dist-info/RECORD
