Metadata-Version: 2.1
Name: xixiang
Version: 0.3.1
Summary: unofficial xixiang python sdk
Home-page: https://github.com/LKI/xixiang
Author: Lirian Su
Author-email: liriansu@gmail.com
License: MIT License
Platform: UNKNOWN
Requires-Dist: requests (>=2.22.0)
